jellycodec/__init__.py
jellycodec/__main__.py
jellycodec-0.1.0.dist-info/licenses/LICENSE
jellycodec-0.1.0.dist-info/METADATA
jellycodec-0.1.0.dist-info/WHEEL
jellycodec-0.1.0.dist-info/entry_points.txt
jellycodec-0.1.0.dist-info/top_level.txt
jellycodec-0.1.0.dist-info/RECORD
