Metadata-Version: 2.4
Name: jellycodec
Version: 0.1.0
Summary: Jellyfin Codec Analyzer — analyze video codecs in your Jellyfin library
Author-email: Ashaan Dalgliesh <ashaandalgliesh@gmail.com>
License: MIT
Classifier: Programming Language :: Python :: 3
Classifier: Programming Language :: Python :: 3 :: Only
Classifier: License :: OSI Approved :: MIT License
Classifier: Operating System :: OS Independent
Requires-Python: >=3.8
License-File: LICENSE
Requires-Dist: requests>=2.25.1
Requires-Dist: python-dotenv>=0.19.0
Dynamic: license-file
